<result>
  <experiment>
    <setting>
      <algorithm name="RandomTree0" libname="weka">
        <parameter name="K" value="1" />
        <parameter name="M" value="0" />
      </algorithm>
      <dataset train="breast-cancer.arff" test="breast-cancer.arff" />
    </setting>
    <evaluation>
      <metric error_rate="2.147483648E9" />
      <metric kappa_statistic="2.147483648E9" />
      <metric mean_absolute_error="2.147483648E9" />
      <metric root_mean_squared_error="2.147483648E9" />
      <metric relative_absolute_error="2.147483648E9" />
      <metric root_relative_squared_error="2.147483648E9" />
    </evaluation>
  </experiment>
  <experiment>
    <setting>
      <algorithm name="RandomTree0" libname="weka">
        <parameter name="K" value="1" />
        <parameter name="M" value="2" />
      </algorithm>
      <dataset train="breast-cancer.arff" test="breast-cancer.arff" />
    </setting>
    <evaluation>
      <metric error_rate="2.147483648E9" />
      <metric kappa_statistic="2.147483648E9" />
      <metric mean_absolute_error="2.147483648E9" />
      <metric root_mean_squared_error="2.147483648E9" />
      <metric relative_absolute_error="2.147483648E9" />
      <metric root_relative_squared_error="2.147483648E9" />
    </evaluation>
  </experiment>
  <experiment>
    <setting>
      <algorithm name="RandomTree0" libname="weka">
        <parameter name="K" value="1" />
        <parameter name="M" value="4" />
      </algorithm>
      <dataset train="breast-cancer.arff" test="breast-cancer.arff" />
    </setting>
    <evaluation>
      <metric error_rate="2.147483648E9" />
      <metric kappa_statistic="2.147483648E9" />
      <metric mean_absolute_error="2.147483648E9" />
      <metric root_mean_squared_error="2.147483648E9" />
      <metric relative_absolute_error="2.147483648E9" />
      <metric root_relative_squared_error="2.147483648E9" />
    </evaluation>
  </experiment>
  <experiment>
    <setting>
      <algorithm name="RandomTree0" libname="weka">
        <parameter name="K" value="1" />
        <parameter name="M" value="6" />
      </algorithm>
      <dataset train="breast-cancer.arff" test="breast-cancer.arff" />
    </setting>
    <evaluation>
      <metric error_rate="2.147483648E9" />
      <metric kappa_statistic="2.147483648E9" />
      <metric mean_absolute_error="2.147483648E9" />
      <metric root_mean_squared_error="2.147483648E9" />
      <metric relative_absolute_error="2.147483648E9" />
      <metric root_relative_squared_error="2.147483648E9" />
    </evaluation>
  </experiment>
  <experiment>
    <setting>
      <algorithm name="RandomTree0" libname="weka">
        <parameter name="K" value="1" />
        <parameter name="M" value="8" />
      </algorithm>
      <dataset train="breast-cancer.arff" test="breast-cancer.arff" />
    </setting>
    <evaluation>
      <metric error_rate="2.147483648E9" />
      <metric kappa_statistic="2.147483648E9" />
      <metric mean_absolute_error="2.147483648E9" />
      <metric root_mean_squared_error="2.147483648E9" />
      <metric relative_absolute_error="2.147483648E9" />
      <metric root_relative_squared_error="2.147483648E9" />
    </evaluation>
  </experiment>
  <experiment>
    <setting>
      <algorithm name="RandomTree0" libname="weka">
        <parameter name="K" value="3" />
        <parameter name="M" value="0" />
      </algorithm>
      <dataset train="breast-cancer.arff" test="breast-cancer.arff" />
    </setting>
    <evaluation>
      <metric error_rate="2.147483648E9" />
      <metric kappa_statistic="2.147483648E9" />
      <metric mean_absolute_error="2.147483648E9" />
      <metric root_mean_squared_error="2.147483648E9" />
      <metric relative_absolute_error="2.147483648E9" />
      <metric root_relative_squared_error="2.147483648E9" />
    </evaluation>
  </experiment>
  <experiment>
    <setting>
      <algorithm name="RandomTree0" libname="weka">
        <parameter name="K" value="3" />
        <parameter name="M" value="2" />
      </algorithm>
      <dataset train="breast-cancer.arff" test="breast-cancer.arff" />
    </setting>
    <evaluation>
      <metric error_rate="2.147483648E9" />
      <metric kappa_statistic="2.147483648E9" />
      <metric mean_absolute_error="2.147483648E9" />
      <metric root_mean_squared_error="2.147483648E9" />
      <metric relative_absolute_error="2.147483648E9" />
      <metric root_relative_squared_error="2.147483648E9" />
    </evaluation>
  </experiment>
  <experiment>
    <setting>
      <algorithm name="RandomTree0" libname="weka">
        <parameter name="K" value="3" />
        <parameter name="M" value="4" />
      </algorithm>
      <dataset train="breast-cancer.arff" test="breast-cancer.arff" />
    </setting>
    <evaluation>
      <metric error_rate="2.147483648E9" />
      <metric kappa_statistic="2.147483648E9" />
      <metric mean_absolute_error="2.147483648E9" />
      <metric root_mean_squared_error="2.147483648E9" />
      <metric relative_absolute_error="2.147483648E9" />
      <metric root_relative_squared_error="2.147483648E9" />
    </evaluation>
  </experiment>
  <experiment>
    <setting>
      <algorithm name="RandomTree0" libname="weka">
        <parameter name="K" value="3" />
        <parameter name="M" value="6" />
      </algorithm>
      <dataset train="breast-cancer.arff" test="breast-cancer.arff" />
    </setting>
    <evaluation>
      <metric error_rate="2.147483648E9" />
      <metric kappa_statistic="2.147483648E9" />
      <metric mean_absolute_error="2.147483648E9" />
      <metric root_mean_squared_error="2.147483648E9" />
      <metric relative_absolute_error="2.147483648E9" />
      <metric root_relative_squared_error="2.147483648E9" />
    </evaluation>
  </experiment>
  <experiment>
    <setting>
      <algorithm name="RandomTree0" libname="weka">
        <parameter name="K" value="3" />
        <parameter name="M" value="8" />
      </algorithm>
      <dataset train="breast-cancer.arff" test="breast-cancer.arff" />
    </setting>
    <evaluation>
      <metric error_rate="2.147483648E9" />
      <metric kappa_statistic="2.147483648E9" />
      <metric mean_absolute_error="2.147483648E9" />
      <metric root_mean_squared_error="2.147483648E9" />
      <metric relative_absolute_error="2.147483648E9" />
      <metric root_relative_squared_error="2.147483648E9" />
    </evaluation>
  </experiment>
  <experiment>
    <setting>
      <algorithm name="RandomTree0" libname="weka">
        <parameter name="K" value="5" />
        <parameter name="M" value="0" />
      </algorithm>
      <dataset train="breast-cancer.arff" test="breast-cancer.arff" />
    </setting>
    <evaluation>
      <metric error_rate="2.147483648E9" />
      <metric kappa_statistic="2.147483648E9" />
      <metric mean_absolute_error="2.147483648E9" />
      <metric root_mean_squared_error="2.147483648E9" />
      <metric relative_absolute_error="2.147483648E9" />
      <metric root_relative_squared_error="2.147483648E9" />
    </evaluation>
  </experiment>
  <experiment>
    <setting>
      <algorithm name="RandomTree0" libname="weka">
        <parameter name="K" value="5" />
        <parameter name="M" value="2" />
      </algorithm>
      <dataset train="breast-cancer.arff" test="breast-cancer.arff" />
    </setting>
    <evaluation>
      <metric error_rate="2.147483648E9" />
      <metric kappa_statistic="2.147483648E9" />
      <metric mean_absolute_error="2.147483648E9" />
      <metric root_mean_squared_error="2.147483648E9" />
      <metric relative_absolute_error="2.147483648E9" />
      <metric root_relative_squared_error="2.147483648E9" />
    </evaluation>
  </experiment>
  <experiment>
    <setting>
      <algorithm name="RandomTree0" libname="weka">
        <parameter name="K" value="5" />
        <parameter name="M" value="4" />
      </algorithm>
      <dataset train="breast-cancer.arff" test="breast-cancer.arff" />
    </setting>
    <evaluation>
      <metric error_rate="2.147483648E9" />
      <metric kappa_statistic="2.147483648E9" />
      <metric mean_absolute_error="2.147483648E9" />
      <metric root_mean_squared_error="2.147483648E9" />
      <metric relative_absolute_error="2.147483648E9" />
      <metric root_relative_squared_error="2.147483648E9" />
    </evaluation>
  </experiment>
  <experiment>
    <setting>
      <algorithm name="RandomTree0" libname="weka">
        <parameter name="K" value="5" />
        <parameter name="M" value="6" />
      </algorithm>
      <dataset train="breast-cancer.arff" test="breast-cancer.arff" />
    </setting>
    <evaluation>
      <metric error_rate="2.147483648E9" />
      <metric kappa_statistic="2.147483648E9" />
      <metric mean_absolute_error="2.147483648E9" />
      <metric root_mean_squared_error="2.147483648E9" />
      <metric relative_absolute_error="2.147483648E9" />
      <metric root_relative_squared_error="2.147483648E9" />
    </evaluation>
  </experiment>
  <experiment>
    <setting>
      <algorithm name="RandomTree0" libname="weka">
        <parameter name="K" value="5" />
        <parameter name="M" value="8" />
      </algorithm>
      <dataset train="breast-cancer.arff" test="breast-cancer.arff" />
    </setting>
    <evaluation>
      <metric error_rate="2.147483648E9" />
      <metric kappa_statistic="2.147483648E9" />
      <metric mean_absolute_error="2.147483648E9" />
      <metric root_mean_squared_error="2.147483648E9" />
      <metric relative_absolute_error="2.147483648E9" />
      <metric root_relative_squared_error="2.147483648E9" />
    </evaluation>
  </experiment>
  <experiment>
    <setting>
      <algorithm name="RandomTree0" libname="weka">
        <parameter name="K" value="7" />
        <parameter name="M" value="0" />
      </algorithm>
      <dataset train="breast-cancer.arff" test="breast-cancer.arff" />
    </setting>
    <evaluation>
      <metric error_rate="2.147483648E9" />
      <metric kappa_statistic="2.147483648E9" />
      <metric mean_absolute_error="2.147483648E9" />
      <metric root_mean_squared_error="2.147483648E9" />
      <metric relative_absolute_error="2.147483648E9" />
      <metric root_relative_squared_error="2.147483648E9" />
    </evaluation>
  </experiment>
  <experiment>
    <setting>
      <algorithm name="RandomTree0" libname="weka">
        <parameter name="K" value="7" />
        <parameter name="M" value="2" />
      </algorithm>
      <dataset train="breast-cancer.arff" test="breast-cancer.arff" />
    </setting>
    <evaluation>
      <metric error_rate="2.147483648E9" />
      <metric kappa_statistic="2.147483648E9" />
      <metric mean_absolute_error="2.147483648E9" />
      <metric root_mean_squared_error="2.147483648E9" />
      <metric relative_absolute_error="2.147483648E9" />
      <metric root_relative_squared_error="2.147483648E9" />
    </evaluation>
  </experiment>
  <experiment>
    <setting>
      <algorithm name="RandomTree0" libname="weka">
        <parameter name="K" value="7" />
        <parameter name="M" value="4" />
      </algorithm>
      <dataset train="breast-cancer.arff" test="breast-cancer.arff" />
    </setting>
    <evaluation>
      <metric error_rate="2.147483648E9" />
      <metric kappa_statistic="2.147483648E9" />
      <metric mean_absolute_error="2.147483648E9" />
      <metric root_mean_squared_error="2.147483648E9" />
      <metric relative_absolute_error="2.147483648E9" />
      <metric root_relative_squared_error="2.147483648E9" />
    </evaluation>
  </experiment>
  <experiment>
    <setting>
      <algorithm name="RandomTree0" libname="weka">
        <parameter name="K" value="7" />
        <parameter name="M" value="6" />
      </algorithm>
      <dataset train="breast-cancer.arff" test="breast-cancer.arff" />
    </setting>
    <evaluation>
      <metric error_rate="2.147483648E9" />
      <metric kappa_statistic="2.147483648E9" />
      <metric mean_absolute_error="2.147483648E9" />
      <metric root_mean_squared_error="2.147483648E9" />
      <metric relative_absolute_error="2.147483648E9" />
      <metric root_relative_squared_error="2.147483648E9" />
    </evaluation>
  </experiment>
  <experiment>
    <setting>
      <algorithm name="RandomTree0" libname="weka">
        <parameter name="K" value="7" />
        <parameter name="M" value="8" />
      </algorithm>
      <dataset train="breast-cancer.arff" test="breast-cancer.arff" />
    </setting>
    <evaluation>
      <metric error_rate="2.147483648E9" />
      <metric kappa_statistic="2.147483648E9" />
      <metric mean_absolute_error="2.147483648E9" />
      <metric root_mean_squared_error="2.147483648E9" />
      <metric relative_absolute_error="2.147483648E9" />
      <metric root_relative_squared_error="2.147483648E9" />
    </evaluation>
  </experiment>
  <experiment>
    <setting>
      <algorithm name="RandomTree0" libname="weka">
        <parameter name="K" value="9" />
        <parameter name="M" value="0" />
      </algorithm>
      <dataset train="breast-cancer.arff" test="breast-cancer.arff" />
    </setting>
    <evaluation>
      <metric error_rate="2.147483648E9" />
      <metric kappa_statistic="2.147483648E9" />
      <metric mean_absolute_error="2.147483648E9" />
      <metric root_mean_squared_error="2.147483648E9" />
      <metric relative_absolute_error="2.147483648E9" />
      <metric root_relative_squared_error="2.147483648E9" />
    </evaluation>
  </experiment>
  <experiment>
    <setting>
      <algorithm name="RandomTree0" libname="weka">
        <parameter name="K" value="9" />
        <parameter name="M" value="2" />
      </algorithm>
      <dataset train="breast-cancer.arff" test="breast-cancer.arff" />
    </setting>
    <evaluation>
      <metric error_rate="2.147483648E9" />
      <metric kappa_statistic="2.147483648E9" />
      <metric mean_absolute_error="2.147483648E9" />
      <metric root_mean_squared_error="2.147483648E9" />
      <metric relative_absolute_error="2.147483648E9" />
      <metric root_relative_squared_error="2.147483648E9" />
    </evaluation>
  </experiment>
  <experiment>
    <setting>
      <algorithm name="RandomTree0" libname="weka">
        <parameter name="K" value="9" />
        <parameter name="M" value="4" />
      </algorithm>
      <dataset train="breast-cancer.arff" test="breast-cancer.arff" />
    </setting>
    <evaluation>
      <metric error_rate="2.147483648E9" />
      <metric kappa_statistic="2.147483648E9" />
      <metric mean_absolute_error="2.147483648E9" />
      <metric root_mean_squared_error="2.147483648E9" />
      <metric relative_absolute_error="2.147483648E9" />
      <metric root_relative_squared_error="2.147483648E9" />
    </evaluation>
  </experiment>
  <experiment>
    <setting>
      <algorithm name="RandomTree0" libname="weka">
        <parameter name="K" value="9" />
        <parameter name="M" value="6" />
      </algorithm>
      <dataset train="breast-cancer.arff" test="breast-cancer.arff" />
    </setting>
    <evaluation>
      <metric error_rate="2.147483648E9" />
      <metric kappa_statistic="2.147483648E9" />
      <metric mean_absolute_error="2.147483648E9" />
      <metric root_mean_squared_error="2.147483648E9" />
      <metric relative_absolute_error="2.147483648E9" />
      <metric root_relative_squared_error="2.147483648E9" />
    </evaluation>
  </experiment>
  <experiment>
    <setting>
      <algorithm name="RandomTree0" libname="weka">
        <parameter name="K" value="9" />
        <parameter name="M" value="8" />
      </algorithm>
      <dataset train="breast-cancer.arff" test="breast-cancer.arff" />
    </setting>
    <evaluation>
      <metric error_rate="2.147483648E9" />
      <metric kappa_statistic="2.147483648E9" />
      <metric mean_absolute_error="2.147483648E9" />
      <metric root_mean_squared_error="2.147483648E9" />
      <metric relative_absolute_error="2.147483648E9" />
      <metric root_relative_squared_error="2.147483648E9" />
    </evaluation>
  </experiment>
  <statistics>
    <metric average_error_rate="2.147483648E9" />
    <metric average_kappa_statistic="2.147483648E9" />
    <metric average_mean_absolute_error="2.147483648E9" />
    <metric average_root_mean_squared_error="2.147483648E9" />
    <metric average_relative_absolute_error="2.147483648E9" />
    <metric average_root_relative_squared_error="2.147483648E9" />
  </statistics>
</result>